[
  {
    "key": "baseline",
    "label": "Baseline",
    "sample_weights": {
      "enabled": false,
      "strategy": "recency",
      "recency": {
        "half_life_days": 365,
        "min_weight": 0.35,
        "normalize": true
      }
    },
    "pooled_log_loss": 0.20368977227604868,
    "pooled_mrr": 0.5261952560210459,
    "composite": -0.05940785573447427,
    "top1_accuracy": 0.3561643835616438,
    "top1_roi": 0.1837671232876712,
    "top1_pnl": 26.829999999999995,
    "fav_top1_accuracy": 0.3424657534246575,
    "fav_roi": 0.04589041095890409,
    "fav_pnl": 6.699999999999997,
    "strong_bets": 30,
    "strong_win_roi": 0.5416666666666666,
    "strong_win_pnl": 16.25,
    "strong_ew_roi": 0.5875,
    "strong_ew_pnl": 17.625,
    "windows": [
      {
        "window": "cheltenham_2023",
        "course": "Cheltenham",
        "train_rows": 25535,
        "val_rows": 444,
        "val_races": 28,
        "best_iteration": 119,
        "log_loss": 0.19485798327330264,
        "mrr": 0.5080935579359949,
        "top1_accuracy": 0.35714285714285715,
        "top1_roi": 0.27499999999999997,
        "top1_pnl": 7.699999999999999,
        "top1_roi_ci_low": -0.4924910714285714,
        "top1_roi_ci_high": 1.2284196428571426,
        "fav_top1_accuracy": 0.32142857142857145,
        "fav_roi": -0.11785714285714285,
        "fav_pnl": -3.3,
        "strong_bets": 4,
        "strong_win_roi": 3.875,
        "strong_win_pnl": 15.5,
        "strong_win_roi_ci_low": -1.0,
        "strong_win_roi_ci_high": 8.75,
        "strong_ew_roi": 2.3671875,
        "strong_ew_pnl": 9.46875
      },
      {
        "window": "cheltenham_2024",
        "course": "Cheltenham",
        "train_rows": 34299,
        "val_rows": 367,
        "val_races": 27,
        "best_iteration": 216,
        "log_loss": 0.20977578961051133,
        "mrr": 0.5541539032767103,
        "top1_accuracy": 0.4074074074074074,
        "top1_roi": 0.02962962962962964,
        "top1_pnl": 0.8000000000000003,
        "top1_roi_ci_low": -0.4678703703703703,
        "top1_roi_ci_high": 0.5427962962962961,
        "fav_top1_accuracy": 0.3333333333333333,
        "fav_roi": -0.28074074074074074,
        "fav_pnl": -7.579999999999999,
        "strong_bets": 3,
        "strong_win_roi": -1.0,
        "strong_win_pnl": -3.0,
        "strong_win_roi_ci_low": -1.0,
        "strong_win_roi_ci_high": -1.0,
        "strong_ew_roi": -0.40499999999999997,
        "strong_ew_pnl": -1.2149999999999999
      },
      {
        "window": "cheltenham_2025",
        "course": "Cheltenham",
        "train_rows": 43061,
        "val_rows": 452,
        "val_races": 28,
        "best_iteration": 82,
        "log_loss": 0.19994759963356948,
        "mrr": 0.4711909763905563,
        "top1_accuracy": 0.2857142857142857,
        "top1_roi": -0.023571428571428577,
        "top1_pnl": -0.6600000000000001,
        "top1_roi_ci_low": -0.5832142857142857,
        "top1_roi_ci_high": 0.7158214285714276,
        "fav_top1_accuracy": 0.32142857142857145,
        "fav_roi": 0.13714285714285715,
        "fav_pnl": 3.84,
        "strong_bets": 3,
        "strong_win_roi": 1.0,
        "strong_win_pnl": 3.0,
        "strong_win_roi_ci_low": -1.0,
        "strong_win_roi_ci_high": 4.0499999999999545,
        "strong_ew_roi": 0.6916666666666668,
        "strong_ew_pnl": 2.075
      },
      {
        "window": "aintree_2023",
        "course": "Aintree",
        "train_rows": 26714,
        "val_rows": 320,
        "val_races": 21,
        "best_iteration": 95,
        "log_loss": 0.1937322290404506,
        "mrr": 0.5495480243379403,
        "top1_accuracy": 0.38095238095238093,
        "top1_roi": 0.4752380952380952,
        "top1_pnl": 9.979999999999999,
        "top1_roi_ci_low": -0.5452380952380952,
        "top1_roi_ci_high": 1.7775238095238093,
        "fav_top1_accuracy": 0.38095238095238093,
        "fav_roi": 0.30857142857142855,
        "fav_pnl": 6.4799999999999995,
        "strong_bets": 9,
        "strong_win_roi": 0.0,
        "strong_win_pnl": 0.0,
        "strong_win_roi_ci_low": -1.0,
        "strong_win_roi_ci_high": 2.0,
        "strong_ew_roi": 1.0680555555555555,
        "strong_ew_pnl": 9.6125
      },
      {
        "window": "aintree_2024",
        "course": "Aintree",
        "train_rows": 35351,
        "val_rows": 279,
        "val_races": 21,
        "best_iteration": 173,
        "log_loss": 0.19400646799522303,
        "mrr": 0.6862640005497147,
        "top1_accuracy": 0.5714285714285714,
        "top1_roi": 1.006190476190476,
        "top1_pnl": 21.129999999999995,
        "top1_roi_ci_low": 0.11269047619047617,
        "top1_roi_ci_high": 2.020523809523809,
        "fav_top1_accuracy": 0.5238095238095238,
        "fav_roi": 0.7442857142857141,
        "fav_pnl": 15.629999999999995,
        "strong_bets": 6,
        "strong_win_roi": 0.3333333333333333,
        "strong_win_pnl": 2.0,
        "strong_win_roi_ci_low": -1.0,
        "strong_win_roi_ci_high": 3.0,
        "strong_ew_roi": -0.005833333333333283,
        "strong_ew_pnl": -0.0349999999999997
      },
      {
        "window": "aintree_2025",
        "course": "Aintree",
        "train_rows": 43873,
        "val_rows": 301,
        "val_races": 21,
        "best_iteration": 70,
        "log_loss": 0.22981856410323495,
        "mrr": 0.38792107363535927,
        "top1_accuracy": 0.14285714285714285,
        "top1_roi": -0.5771428571428571,
        "top1_pnl": -12.12,
        "top1_roi_ci_low": -1.0,
        "top1_roi_ci_high": -0.060488095238096305,
        "fav_top1_accuracy": 0.19047619047619047,
        "fav_roi": -0.3985714285714285,
        "fav_pnl": -8.37,
        "strong_bets": 5,
        "strong_win_roi": -0.25,
        "strong_win_pnl": -1.25,
        "strong_win_roi_ci_low": -1.0,
        "strong_win_roi_ci_high": 1.25,
        "strong_ew_roi": -0.45625,
        "strong_ew_pnl": -2.28125
      }
    ]
  },
  {
    "key": "recency_1095d_floor_0_5",
    "label": "Recency 1095d / floor 0.50",
    "sample_weights": {
      "enabled": true,
      "strategy": "recency",
      "recency": {
        "half_life_days": 1095.0,
        "min_weight": 0.5,
        "normalize": true
      }
    },
    "pooled_log_loss": 0.20413993589573262,
    "pooled_mrr": 0.5113911400722178,
    "composite": -0.051555634140376255,
    "top1_accuracy": 0.3287671232876712,
    "top1_roi": 0.032397260273972564,
    "top1_pnl": 4.729999999999994,
    "fav_top1_accuracy": 0.3424657534246575,
    "fav_roi": 0.04589041095890409,
    "fav_pnl": 6.699999999999997,
    "strong_bets": 38,
    "strong_win_roi": 0.3973684210526316,
    "strong_win_pnl": 15.1,
    "strong_ew_roi": 0.4479605263157895,
    "strong_ew_pnl": 17.0225,
    "windows": [
      {
        "window": "cheltenham_2023",
        "course": "Cheltenham",
        "train_rows": 25535,
        "val_rows": 444,
        "val_races": 28,
        "best_iteration": 113,
        "log_loss": 0.19617113343948203,
        "mrr": 0.47818484251754934,
        "top1_accuracy": 0.2857142857142857,
        "top1_roi": -0.19285714285714287,
        "top1_pnl": -5.4,
        "top1_roi_ci_low": -0.6737946428571429,
        "top1_roi_ci_high": 0.39490178571428536,
        "fav_top1_accuracy": 0.32142857142857145,
        "fav_roi": -0.11785714285714285,
        "fav_pnl": -3.3,
        "strong_bets": 5,
        "strong_win_roi": 3.6,
        "strong_win_pnl": 18.0,
        "strong_win_roi_ci_low": 0.4,
        "strong_win_roi_ci_high": 6.7,
        "strong_ew_roi": 2.07,
        "strong_ew_pnl": 10.35
      },
      {
        "window": "cheltenham_2024",
        "course": "Cheltenham",
        "train_rows": 34299,
        "val_rows": 367,
        "val_races": 27,
        "best_iteration": 158,
        "log_loss": 0.21249022945716947,
        "mrr": 0.5330940988835726,
        "top1_accuracy": 0.37037037037037035,
        "top1_roi": -0.1,
        "top1_pnl": -2.7,
        "top1_roi_ci_low": -0.5490555555555556,
        "top1_roi_ci_high": 0.44447222222222205,
        "fav_top1_accuracy": 0.3333333333333333,
        "fav_roi": -0.28074074074074074,
        "fav_pnl": -7.579999999999999,
        "strong_bets": 5,
        "strong_win_roi": -1.0,
        "strong_win_pnl": -5.0,
        "strong_win_roi_ci_low": -1.0,
        "strong_win_roi_ci_high": -1.0,
        "strong_ew_roi": -0.643,
        "strong_ew_pnl": -3.215
      },
      {
        "window": "cheltenham_2025",
        "course": "Cheltenham",
        "train_rows": 43061,
        "val_rows": 452,
        "val_races": 28,
        "best_iteration": 206,
        "log_loss": 0.1953541865325118,
        "mrr": 0.47696995464852604,
        "top1_accuracy": 0.2857142857142857,
        "top1_roi": -0.023571428571428577,
        "top1_pnl": -0.6600000000000001,
        "top1_roi_ci_low": -0.5832142857142857,
        "top1_roi_ci_high": 0.7158214285714276,
        "fav_top1_accuracy": 0.32142857142857145,
        "fav_roi": 0.13714285714285715,
        "fav_pnl": 3.84,
        "strong_bets": 6,
        "strong_win_roi": 0.4166666666666667,
        "strong_win_pnl": 2.5,
        "strong_win_roi_ci_low": -1.0,
        "strong_win_roi_ci_high": 2.4166666666666665,
        "strong_ew_roi": 0.4635416666666667,
        "strong_ew_pnl": 2.78125
      },
      {
        "window": "aintree_2023",
        "course": "Aintree",
        "train_rows": 26714,
        "val_rows": 320,
        "val_races": 21,
        "best_iteration": 79,
        "log_loss": 0.19342027064153772,
        "mrr": 0.543452380952381,
        "top1_accuracy": 0.38095238095238093,
        "top1_roi": 0.4752380952380952,
        "top1_pnl": 9.979999999999999,
        "top1_roi_ci_low": -0.5452380952380952,
        "top1_roi_ci_high": 1.7775238095238093,
        "fav_top1_accuracy": 0.38095238095238093,
        "fav_roi": 0.30857142857142855,
        "fav_pnl": 6.4799999999999995,
        "strong_bets": 10,
        "strong_win_roi": -0.1,
        "strong_win_pnl": -1.0,
        "strong_win_roi_ci_low": -1.0,
        "strong_win_roi_ci_high": 1.7,
        "strong_ew_roi": 0.80975,
        "strong_ew_pnl": 8.0975
      },
      {
        "window": "aintree_2024",
        "course": "Aintree",
        "train_rows": 35351,
        "val_rows": 279,
        "val_races": 21,
        "best_iteration": 183,
        "log_loss": 0.19731116633885026,
        "mrr": 0.6495670995670996,
        "top1_accuracy": 0.5238095238095238,
        "top1_roi": 0.7442857142857141,
        "top1_pnl": 15.629999999999995,
        "top1_roi_ci_low": -0.11961904761904761,
        "top1_roi_ci_high": 1.6586190476190477,
        "fav_top1_accuracy": 0.5238095238095238,
        "fav_roi": 0.7442857142857141,
        "fav_pnl": 15.629999999999995,
        "strong_bets": 9,
        "strong_win_roi": 0.39999999999999997,
        "strong_win_pnl": 3.5999999999999996,
        "strong_win_roi_ci_low": -1.0,
        "strong_win_roi_ci_high": 2.2222222222222223,
        "strong_ew_roi": 0.1363888888888889,
        "strong_ew_pnl": 1.2275
      },
      {
        "window": "aintree_2025",
        "course": "Aintree",
        "train_rows": 43873,
        "val_rows": 301,
        "val_races": 21,
        "best_iteration": 71,
        "log_loss": 0.23009262896484428,
        "mrr": 0.38707846386417816,
        "top1_accuracy": 0.14285714285714285,
        "top1_roi": -0.5771428571428571,
        "top1_pnl": -12.12,
        "top1_roi_ci_low": -1.0,
        "top1_roi_ci_high": -0.060488095238096305,
        "fav_top1_accuracy": 0.19047619047619047,
        "fav_roi": -0.3985714285714285,
        "fav_pnl": -8.37,
        "strong_bets": 3,
        "strong_win_roi": -1.0,
        "strong_win_pnl": -3.0,
        "strong_win_roi_ci_low": -1.0,
        "strong_win_roi_ci_high": -1.0,
        "strong_ew_roi": -0.7395833333333334,
        "strong_ew_pnl": -2.21875
      }
    ]
  },
  {
    "key": "recency_1095d_floor_0_35",
    "label": "Recency 1095d / floor 0.35",
    "sample_weights": {
      "enabled": true,
      "strategy": "recency",
      "recency": {
        "half_life_days": 1095.0,
        "min_weight": 0.35,
        "normalize": true
      }
    },
    "pooled_log_loss": 0.20409491574550434,
    "pooled_mrr": 0.5108647684536191,
    "composite": -0.05133746848130519,
    "top1_accuracy": 0.3287671232876712,
    "top1_roi": 0.05705479452054792,
    "top1_pnl": 8.329999999999997,
    "fav_top1_accuracy": 0.3424657534246575,
    "fav_roi": 0.04589041095890409,
    "fav_pnl": 6.699999999999997,
    "strong_bets": 43,
    "strong_win_roi": 0.9302325581395349,
    "strong_win_pnl": 40.0,
    "strong_ew_roi": 0.6203197674418605,
    "strong_ew_pnl": 26.67375,
    "windows": [
      {
        "window": "cheltenham_2023",
        "course": "Cheltenham",
        "train_rows": 25535,
        "val_rows": 444,
        "val_races": 28,
        "best_iteration": 117,
        "log_loss": 0.19484568690154383,
        "mrr": 0.5226859763043974,
        "top1_accuracy": 0.35714285714285715,
        "top1_roi": 0.27499999999999997,
        "top1_pnl": 7.699999999999999,
        "top1_roi_ci_low": -0.4924910714285714,
        "top1_roi_ci_high": 1.2284196428571426,
        "fav_top1_accuracy": 0.32142857142857145,
        "fav_roi": -0.11785714285714285,
        "fav_pnl": -3.3,
        "strong_bets": 5,
        "strong_win_roi": 4.4,
        "strong_win_pnl": 22.0,
        "strong_win_roi_ci_low": 0.5,
        "strong_win_roi_ci_high": 8.1,
        "strong_ew_roi": 2.55,
        "strong_ew_pnl": 12.75
      },
      {
        "window": "cheltenham_2024",
        "course": "Cheltenham",
        "train_rows": 34299,
        "val_rows": 367,
        "val_races": 27,
        "best_iteration": 196,
        "log_loss": 0.2127373949585828,
        "mrr": 0.5113168724279835,
        "top1_accuracy": 0.3333333333333333,
        "top1_roi": -0.3037037037037037,
        "top1_pnl": -8.2,
        "top1_roi_ci_low": -0.6662685185185184,
        "top1_roi_ci_high": 0.0895277777777777,
        "fav_top1_accuracy": 0.3333333333333333,
        "fav_roi": -0.28074074074074074,
        "fav_pnl": -7.579999999999999,
        "strong_bets": 5,
        "strong_win_roi": -1.0,
        "strong_win_pnl": -5.0,
        "strong_win_roi_ci_low": -1.0,
        "strong_win_roi_ci_high": -1.0,
        "strong_ew_roi": -0.643,
        "strong_ew_pnl": -3.215
      },
      {
        "window": "cheltenham_2025",
        "course": "Cheltenham",
        "train_rows": 43061,
        "val_rows": 452,
        "val_races": 28,
        "best_iteration": 201,
        "log_loss": 0.19647064701603054,
        "mrr": 0.47248441043083905,
        "top1_accuracy": 0.2857142857142857,
        "top1_roi": -0.023571428571428577,
        "top1_pnl": -0.6600000000000001,
        "top1_roi_ci_low": -0.5832142857142857,
        "top1_roi_ci_high": 0.7158214285714276,
        "fav_top1_accuracy": 0.32142857142857145,
        "fav_roi": 0.13714285714285715,
        "fav_pnl": 3.84,
        "strong_bets": 8,
        "strong_win_roi": 1.4375,
        "strong_win_pnl": 11.5,
        "strong_win_roi_ci_low": -0.25,
        "strong_win_roi_ci_high": 3.6578124999999986,
        "strong_ew_roi": 1.0226562499999998,
        "strong_ew_pnl": 8.181249999999999
      },
      {
        "window": "aintree_2023",
        "course": "Aintree",
        "train_rows": 26714,
        "val_rows": 320,
        "val_races": 21,
        "best_iteration": 176,
        "log_loss": 0.19266838988558133,
        "mrr": 0.5213529856387,
        "top1_accuracy": 0.3333333333333333,
        "top1_roi": 0.28476190476190477,
        "top1_pnl": 5.98,
        "top1_roi_ci_low": -0.6675714285714286,
        "top1_roi_ci_high": 1.4922023809523808,
        "fav_top1_accuracy": 0.38095238095238093,
        "fav_roi": 0.30857142857142855,
        "fav_pnl": 6.4799999999999995,
        "strong_bets": 12,
        "strong_win_roi": 1.1666666666666667,
        "strong_win_pnl": 14.0,
        "strong_win_roi_ci_low": -1.0,
        "strong_win_roi_ci_high": 4.666666666666667,
        "strong_ew_roi": 1.0948958333333332,
        "strong_ew_pnl": 13.138749999999998
      },
      {
        "window": "aintree_2024",
        "course": "Aintree",
        "train_rows": 35351,
        "val_rows": 279,
        "val_races": 21,
        "best_iteration": 173,
        "log_loss": 0.19658816389886483,
        "mrr": 0.6500555000555,
        "top1_accuracy": 0.5238095238095238,
        "top1_roi": 0.7442857142857141,
        "top1_pnl": 15.629999999999995,
        "top1_roi_ci_low": -0.11961904761904761,
        "top1_roi_ci_high": 1.6586190476190477,
        "fav_top1_accuracy": 0.5238095238095238,
        "fav_roi": 0.7442857142857141,
        "fav_pnl": 15.629999999999995,
        "strong_bets": 9,
        "strong_win_roi": 0.16666666666666666,
        "strong_win_pnl": 1.5,
        "strong_win_roi_ci_low": -1.0,
        "strong_win_roi_ci_high": 2.2222222222222223,
        "strong_ew_roi": -0.02013888888888888,
        "strong_ew_pnl": -0.1812499999999999
      },
      {
        "window": "aintree_2025",
        "course": "Aintree",
        "train_rows": 43873,
        "val_rows": 301,
        "val_races": 21,
        "best_iteration": 55,
        "log_loss": 0.23125921181242282,
        "mrr": 0.38729286586429434,
        "top1_accuracy": 0.14285714285714285,
        "top1_roi": -0.5771428571428571,
        "top1_pnl": -12.12,
        "top1_roi_ci_low": -1.0,
        "top1_roi_ci_high": -0.060488095238096305,
        "fav_top1_accuracy": 0.19047619047619047,
        "fav_roi": -0.3985714285714285,
        "fav_pnl": -8.37,
        "strong_bets": 4,
        "strong_win_roi": -1.0,
        "strong_win_pnl": -4.0,
        "strong_win_roi_ci_low": -1.0,
        "strong_win_roi_ci_high": -1.0,
        "strong_ew_roi": -1.0,
        "strong_ew_pnl": -4.0
      }
    ]
  },
  {
    "key": "recency_1460d_floor_0_5",
    "label": "Recency 1460d / floor 0.50",
    "sample_weights": {
      "enabled": true,
      "strategy": "recency",
      "recency": {
        "half_life_days": 1460.0,
        "min_weight": 0.5,
        "normalize": true
      }
    },
    "pooled_log_loss": 0.2055521361972172,
    "pooled_mrr": 0.5071977736956155,
    "composite": -0.048046750650590525,
    "top1_accuracy": 0.3287671232876712,
    "top1_roi": -0.01486301369863016,
    "top1_pnl": -2.1700000000000035,
    "fav_top1_accuracy": 0.3424657534246575,
    "fav_roi": 0.04589041095890409,
    "fav_pnl": 6.699999999999997,
    "strong_bets": 32,
    "strong_win_roi": 0.28125,
    "strong_win_pnl": 9.0,
    "strong_ew_roi": 0.9297265625,
    "strong_ew_pnl": 29.75125,
    "windows": [
      {
        "window": "cheltenham_2023",
        "course": "Cheltenham",
        "train_rows": 25535,
        "val_rows": 444,
        "val_races": 28,
        "best_iteration": 108,
        "log_loss": 0.19537312760247713,
        "mrr": 0.495391810570382,
        "top1_accuracy": 0.32142857142857145,
        "top1_roi": -0.11785714285714285,
        "top1_pnl": -3.3,
        "top1_roi_ci_low": -0.6022321428571429,
        "top1_roi_ci_high": 0.5065178571428565,
        "fav_top1_accuracy": 0.32142857142857145,
        "fav_roi": -0.11785714285714285,
        "fav_pnl": -3.3,
        "strong_bets": 8,
        "strong_win_roi": 0.9375,
        "strong_win_pnl": 7.5,
        "strong_win_roi_ci_low": -1.0,
        "strong_win_roi_ci_high": 3.25,
        "strong_ew_roi": 1.575,
        "strong_ew_pnl": 12.6
      },
      {
        "window": "cheltenham_2024",
        "course": "Cheltenham",
        "train_rows": 34299,
        "val_rows": 367,
        "val_races": 27,
        "best_iteration": 85,
        "log_loss": 0.21530981413924521,
        "mrr": 0.5141921160927009,
        "top1_accuracy": 0.3333333333333333,
        "top1_roi": -0.3037037037037037,
        "top1_pnl": -8.2,
        "top1_roi_ci_low": -0.6662685185185184,
        "top1_roi_ci_high": 0.0895277777777777,
        "fav_top1_accuracy": 0.3333333333333333,
        "fav_roi": -0.28074074074074074,
        "fav_pnl": -7.579999999999999,
        "strong_bets": 4,
        "strong_win_roi": -1.0,
        "strong_win_pnl": -4.0,
        "strong_win_roi_ci_low": -1.0,
        "strong_win_roi_ci_high": -1.0,
        "strong_ew_roi": 0.55875,
        "strong_ew_pnl": 2.235
      },
      {
        "window": "cheltenham_2025",
        "course": "Cheltenham",
        "train_rows": 43061,
        "val_rows": 452,
        "val_races": 28,
        "best_iteration": 102,
        "log_loss": 0.1993861326114673,
        "mrr": 0.4670209750566893,
        "top1_accuracy": 0.2857142857142857,
        "top1_roi": -0.023571428571428577,
        "top1_pnl": -0.6600000000000001,
        "top1_roi_ci_low": -0.5832142857142857,
        "top1_roi_ci_high": 0.7158214285714276,
        "fav_top1_accuracy": 0.32142857142857145,
        "fav_roi": 0.13714285714285715,
        "fav_pnl": 3.84,
        "strong_bets": 5,
        "strong_win_roi": 0.2,
        "strong_win_pnl": 1.0,
        "strong_win_roi_ci_low": -1.0,
        "strong_win_roi_ci_high": 2.6,
        "strong_ew_roi": 1.90875,
        "strong_ew_pnl": 9.54375
      },
      {
        "window": "aintree_2023",
        "course": "Aintree",
        "train_rows": 26714,
        "val_rows": 320,
        "val_races": 21,
        "best_iteration": 92,
        "log_loss": 0.19477108264630122,
        "mrr": 0.5453342953342953,
        "top1_accuracy": 0.38095238095238093,
        "top1_roi": 0.30857142857142855,
        "top1_pnl": 6.4799999999999995,
        "top1_roi_ci_low": -0.46973809523809523,
        "top1_roi_ci_high": 1.4838809523809522,
        "fav_top1_accuracy": 0.38095238095238093,
        "fav_roi": 0.30857142857142855,
        "fav_pnl": 6.4799999999999995,
        "strong_bets": 8,
        "strong_win_roi": 0.125,
        "strong_win_pnl": 1.0,
        "strong_win_roi_ci_low": -1.0,
        "strong_win_roi_ci_high": 2.375,
        "strong_ew_roi": 0.5746875,
        "strong_ew_pnl": 4.5975
      },
      {
        "window": "aintree_2024",
        "course": "Aintree",
        "train_rows": 35351,
        "val_rows": 279,
        "val_races": 21,
        "best_iteration": 170,
        "log_loss": 0.19781769132341034,
        "mrr": 0.6356009070294784,
        "top1_accuracy": 0.5238095238095238,
        "top1_roi": 0.7442857142857141,
        "top1_pnl": 15.629999999999995,
        "top1_roi_ci_low": -0.11961904761904761,
        "top1_roi_ci_high": 1.6586190476190477,
        "fav_top1_accuracy": 0.5238095238095238,
        "fav_roi": 0.7442857142857141,
        "fav_pnl": 15.629999999999995,
        "strong_bets": 5,
        "strong_win_roi": 1.1,
        "strong_win_pnl": 5.5,
        "strong_win_roi_ci_low": -1.0,
        "strong_win_roi_ci_high": 4.3,
        "strong_ew_roi": 0.555,
        "strong_ew_pnl": 2.7750000000000004
      },
      {
        "window": "aintree_2025",
        "course": "Aintree",
        "train_rows": 43873,
        "val_rows": 301,
        "val_races": 21,
        "best_iteration": 74,
        "log_loss": 0.2306549688604019,
        "mrr": 0.38564653809014715,
        "top1_accuracy": 0.14285714285714285,
        "top1_roi": -0.5771428571428571,
        "top1_pnl": -12.12,
        "top1_roi_ci_low": -1.0,
        "top1_roi_ci_high": -0.060488095238096305,
        "fav_top1_accuracy": 0.19047619047619047,
        "fav_roi": -0.3985714285714285,
        "fav_pnl": -8.37,
        "strong_bets": 2,
        "strong_win_roi": -1.0,
        "strong_win_pnl": -2.0,
        "strong_win_roi_ci_low": -1.0,
        "strong_win_roi_ci_high": -1.0,
        "strong_ew_roi": -1.0,
        "strong_ew_pnl": -2.0
      }
    ]
  },
  {
    "key": "recency_1460d_floor_0_35",
    "label": "Recency 1460d / floor 0.35",
    "sample_weights": {
      "enabled": true,
      "strategy": "recency",
      "recency": {
        "half_life_days": 1460.0,
        "min_weight": 0.35,
        "normalize": true
      }
    },
    "pooled_log_loss": 0.20499394228374443,
    "pooled_mrr": 0.5035321093745851,
    "composite": -0.046772112403548144,
    "top1_accuracy": 0.3150684931506849,
    "top1_roi": 0.016164383561643795,
    "top1_pnl": 2.359999999999994,
    "fav_top1_accuracy": 0.3424657534246575,
    "fav_roi": 0.04589041095890409,
    "fav_pnl": 6.699999999999997,
    "strong_bets": 38,
    "strong_win_roi": 0.2921052631578947,
    "strong_win_pnl": 11.1,
    "strong_ew_roi": 0.6247368421052631,
    "strong_ew_pnl": 23.74,
    "windows": [
      {
        "window": "cheltenham_2023",
        "course": "Cheltenham",
        "train_rows": 25535,
        "val_rows": 444,
        "val_races": 28,
        "best_iteration": 75,
        "log_loss": 0.19676941216773566,
        "mrr": 0.47795404000761144,
        "top1_accuracy": 0.2857142857142857,
        "top1_roi": 0.08392857142857142,
        "top1_pnl": 2.3499999999999996,
        "top1_roi_ci_low": -0.6655535714285714,
        "top1_roi_ci_high": 1.0487946428571429,
        "fav_top1_accuracy": 0.32142857142857145,
        "fav_roi": -0.11785714285714285,
        "fav_pnl": -3.3,
        "strong_bets": 4,
        "strong_win_roi": 2.875,
        "strong_win_pnl": 11.5,
        "strong_win_roi_ci_low": -1.0,
        "strong_win_roi_ci_high": 6.75,
        "strong_ew_roi": 3.759375,
        "strong_ew_pnl": 15.0375
      },
      {
        "window": "cheltenham_2024",
        "course": "Cheltenham",
        "train_rows": 34299,
        "val_rows": 367,
        "val_races": 27,
        "best_iteration": 101,
        "log_loss": 0.21415167959887965,
        "mrr": 0.5143346002823127,
        "top1_accuracy": 0.3333333333333333,
        "top1_roi": -0.19703703703703704,
        "top1_pnl": -5.32,
        "top1_roi_ci_low": -0.6153981481481481,
        "top1_roi_ci_high": 0.3434537037037027,
        "fav_top1_accuracy": 0.3333333333333333,
        "fav_roi": -0.28074074074074074,
        "fav_pnl": -7.579999999999999,
        "strong_bets": 4,
        "strong_win_roi": -1.0,
        "strong_win_pnl": -4.0,
        "strong_win_roi_ci_low": -1.0,
        "strong_win_roi_ci_high": -1.0,
        "strong_ew_roi": -0.81625,
        "strong_ew_pnl": -3.265
      },
      {
        "window": "cheltenham_2025",
        "course": "Cheltenham",
        "train_rows": 43061,
        "val_rows": 452,
        "val_races": 28,
        "best_iteration": 144,
        "log_loss": 0.19742258722142117,
        "mrr": 0.45010629251700685,
        "top1_accuracy": 0.25,
        "top1_roi": -0.2914285714285714,
        "top1_pnl": -8.16,
        "top1_roi_ci_low": -0.6637142857142857,
        "top1_roi_ci_high": 0.23840178571428572,
        "fav_top1_accuracy": 0.32142857142857145,
        "fav_roi": 0.13714285714285715,
        "fav_pnl": 3.84,
        "strong_bets": 7,
        "strong_win_roi": 0.7142857142857143,
        "strong_win_pnl": 5.0,
        "strong_win_roi_ci_low": -0.6428571428571429,
        "strong_win_roi_ci_high": 2.5035714285714255,
        "strong_ew_roi": 0.6116071428571429,
        "strong_ew_pnl": 4.28125
      },
      {
        "window": "aintree_2023",
        "course": "Aintree",
        "train_rows": 26714,
        "val_rows": 320,
        "val_races": 21,
        "best_iteration": 118,
        "log_loss": 0.1941425815001847,
        "mrr": 0.5423740941598084,
        "top1_accuracy": 0.38095238095238093,
        "top1_roi": 0.4752380952380952,
        "top1_pnl": 9.979999999999999,
        "top1_roi_ci_low": -0.5452380952380952,
        "top1_roi_ci_high": 1.7775238095238093,
        "fav_top1_accuracy": 0.38095238095238093,
        "fav_roi": 0.30857142857142855,
        "fav_pnl": 6.4799999999999995,
        "strong_bets": 11,
        "strong_win_roi": -0.18181818181818182,
        "strong_win_pnl": -2.0,
        "strong_win_roi_ci_low": -1.0,
        "strong_win_roi_ci_high": 1.4545454545454546,
        "strong_ew_roi": 0.4129545454545454,
        "strong_ew_pnl": 4.5424999999999995
      },
      {
        "window": "aintree_2024",
        "course": "Aintree",
        "train_rows": 35351,
        "val_rows": 279,
        "val_races": 21,
        "best_iteration": 172,
        "log_loss": 0.19500194878065988,
        "mrr": 0.6482964125821267,
        "top1_accuracy": 0.5238095238095238,
        "top1_roi": 0.7442857142857141,
        "top1_pnl": 15.629999999999995,
        "top1_roi_ci_low": -0.11961904761904761,
        "top1_roi_ci_high": 1.6586190476190477,
        "fav_top1_accuracy": 0.5238095238095238,
        "fav_roi": 0.7442857142857141,
        "fav_pnl": 15.629999999999995,
        "strong_bets": 8,
        "strong_win_roi": 0.575,
        "strong_win_pnl": 4.6,
        "strong_win_roi_ci_low": -0.8753124999999996,
        "strong_win_roi_ci_high": 2.575,
        "strong_ew_roi": 0.39296875000000003,
        "strong_ew_pnl": 3.1437500000000003
      },
      {
        "window": "aintree_2025",
        "course": "Aintree",
        "train_rows": 43873,
        "val_rows": 301,
        "val_races": 21,
        "best_iteration": 55,
        "log_loss": 0.23247544443358542,
        "mrr": 0.38812721669864525,
        "top1_accuracy": 0.14285714285714285,
        "top1_roi": -0.5771428571428571,
        "top1_pnl": -12.12,
        "top1_roi_ci_low": -1.0,
        "top1_roi_ci_high": -0.060488095238096305,
        "fav_top1_accuracy": 0.19047619047619047,
        "fav_roi": -0.3985714285714285,
        "fav_pnl": -8.37,
        "strong_bets": 4,
        "strong_win_roi": -1.0,
        "strong_win_pnl": -4.0,
        "strong_win_roi_ci_low": -1.0,
        "strong_win_roi_ci_high": -1.0,
        "strong_ew_roi": 0.0,
        "strong_ew_pnl": 0.0
      }
    ]
  }
]